README.md
setup.py
brotli_middleware/__init__.py
brotli_middleware.egg-info/PKG-INFO
brotli_middleware.egg-info/SOURCES.txt
brotli_middleware.egg-info/dependency_links.txt
brotli_middleware.egg-info/not-zip-safe
brotli_middleware.egg-info/requires.txt
brotli_middleware.egg-info/top_level.txt