Metadata-Version: 1.2
Name: brotli-middleware
Version: 0.3
Summary: A compression AGSI middleware using brotli
Home-page: https://github.com/fullonic/brotli_middleware
Author: Diogo B Freitas
Author-email: somnium@riseup.net
License: MIT
Platform: any
Classifier: Environment :: Web Environment
Classifier: Operating System :: OS Independent
Classifier: Programming Language :: Python :: 3.6
Classifier: Programming Language :: Python :: 3.7
Classifier: Programming Language :: Python :: 3.8
Requires-Python: >=3.6
